nfdrs4py/__init__.py
nfdrs4py/_nfdrs4_bindings.cp311-win_amd64.pyd
nfdrs4py/nfdrs4_bindings.py
nfdrs4py/nfdrs4py.py
nfdrs4py-0.2.2.dist-info/METADATA
nfdrs4py-0.2.2.dist-info/WHEEL
nfdrs4py-0.2.2.dist-info/top_level.txt
nfdrs4py-0.2.2.dist-info/RECORD
